s3dlio-0.9.31.dist-info/METADATA
s3dlio-0.9.31.dist-info/WHEEL
s3dlio-0.9.31.dist-info/licenses/LICENSE
s3dlio.libs/libaec-4fd52145.so.0
s3dlio.libs/libbrotlicommon-a91ead09.so.1
s3dlio.libs/libbrotlidec-64d8a501.so.1
s3dlio.libs/libcom_err-022943b3.so.2
s3dlio.libs/libcrypto-c19c2cf8.so.3
s3dlio.libs/libcurl-bc0f65f0.so.4
s3dlio.libs/libffi-00f593fe.so.8
s3dlio.libs/libgmp-9961d507.so.10
s3dlio.libs/libgnutls-96137275.so.30
s3dlio.libs/libgssapi_krb5-b9a20df7.so.2
s3dlio.libs/libhdf5_serial-aa9c9c40.so.103
s3dlio.libs/libhogweed-c3c60613.so.6
s3dlio.libs/libidn2-6b78fa7e.so.0
s3dlio.libs/libk5crypto-8394027f.so.3
s3dlio.libs/libkeyutils-f4821441.so.1
s3dlio.libs/libkrb5-52c143c9.so.3
s3dlio.libs/libkrb5support-8e1ef5a4.so.0
s3dlio.libs/liblber-fda95e45.so.2
s3dlio.libs/libldap-ffed3485.so.2
s3dlio.libs/libnettle-a245ed91.so.8
s3dlio.libs/libnghttp2-ae21a6a7.so.14
s3dlio.libs/libp11-kit-c6b469a0.so.0
s3dlio.libs/libpsl-ae6c5a9a.so.5
s3dlio.libs/librtmp-15a2a75e.so.1
s3dlio.libs/libsasl2-a0f410ad.so.2
s3dlio.libs/libssh-ed3828e1.so.4
s3dlio.libs/libssl-63597a81.so.3
s3dlio.libs/libsz-e73fa402.so.2
s3dlio.libs/libtasn1-7c9c7830.so.6
s3dlio.libs/libunistring-e08e4cf4.so.5
s3dlio.libs/libzstd-0a2128bc.so.1
s3dlio/__init__.py
s3dlio/_pymod.cpython-313-x86_64-linux-gnu.so
s3dlio/integrations/__init__.py
s3dlio/integrations/dlio/__init__.py
s3dlio/integrations/dlio/s3_torch_storage.py
s3dlio/integrations/dlio/s3dlio_storage.py
s3dlio/jax_tf.py
s3dlio/torch.py
s3dlio-0.9.31.dist-info/RECORD
