Metadata-Version: 2.4
Name: s3dlio
Version: 0.9.31
Requires-Dist: numpy>=2.0.0
Requires-Dist: torch>=2.0.0 ; extra == 'torch'
Requires-Dist: jax>=0.4.0 ; extra == 'jax'
Requires-Dist: jaxlib>=0.4.0 ; extra == 'jax'
Requires-Dist: tensorflow>=2.16.0 ; extra == 'tensorflow'
Requires-Dist: torch>=2.0.0 ; extra == 'all'
Requires-Dist: jax>=0.4.0 ; extra == 'all'
Requires-Dist: jaxlib>=0.4.0 ; extra == 'all'
Requires-Dist: tensorflow>=2.16.0 ; extra == 'all'
Requires-Dist: pytest>=8.0.0 ; extra == 'dev'
Requires-Dist: pytest-asyncio>=0.23.0 ; extra == 'dev'
Requires-Dist: h5py>=3.0.0 ; extra == 'dev'
Requires-Dist: maturin>=1.0.0 ; extra == 'dev'
Requires-Dist: patchelf>=0.17.0 ; extra == 'dev'
Provides-Extra: torch
Provides-Extra: jax
Provides-Extra: tensorflow
Provides-Extra: all
Provides-Extra: dev
License-File: LICENSE
Summary: High-performance S3, Azure, GCS, and file system operations for AI/ML
Author-email: Russ Fellows <russ.fellows@gmail.com>
License: Apache-2.0
Requires-Python: >=3.12
